kobana/__init__.py
kobana/client.py
kobana/configuration.py
kobana/connection.py
kobana/errors.py
kobana/resources/__init__.py
kobana/resources/base.py
kobana/resources/connection.py
kobana/resources/charge/__init__.py
kobana/resources/charge/bank_billet.py
kobana/resources/charge/pix.py
kobana/resources/financial/__init__.py
kobana/resources/financial/account.py
kobana/resources/financial/bank_billet_account.py
kobana-0.1.0.dist-info/licenses/LICENSE
kobana-0.1.0.dist-info/METADATA
kobana-0.1.0.dist-info/WHEEL
kobana-0.1.0.dist-info/top_level.txt
kobana-0.1.0.dist-info/RECORD
