Metadata-Version: 2.4
Name: kobana
Version: 0.1.0
Summary: Python SDK client for Kobana financial automation API
Author-email: Kobana <contato@kobana.com.br>
License: MIT
Project-URL: Homepage, https://github.com/universokobana/kobana-python-client
Project-URL: Documentation, https://ai.kobana.com.br
Project-URL: Repository, https://github.com/universokobana/kobana-python-client
Project-URL: Issues, https://github.com/universokobana/kobana-python-client/issues
Keywords: kobana,api,sdk,financial,boleto,pix,banking
Classifier: Development Status :: 4 - Beta
Classifier: Intended Audience :: Developers
Classifier: License :: OSI Approved :: MIT License
Classifier: Operating System :: OS Independent
Classifier: Programming Language :: Python :: 3
Classifier: Programming Language :: Python :: 3.10
Classifier: Programming Language :: Python :: 3.11
Classifier: Programming Language :: Python :: 3.12
Classifier: Programming Language :: Python :: 3.13
Classifier: Topic :: Software Development :: Libraries :: Python Modules
Classifier: Topic :: Office/Business :: Financial
Requires-Python: >=3.10
License-File: LICENSE
Requires-Dist: httpx>=0.27.0
Requires-Dist: python-dotenv>=1.0.0
Provides-Extra: dev
Requires-Dist: pytest>=8.0.0; extra == "dev"
Requires-Dist: pytest-vcr>=1.0.2; extra == "dev"
Requires-Dist: vcrpy>=6.0.0; extra == "dev"
Requires-Dist: pytest-cov>=4.0.0; extra == "dev"
Requires-Dist: ruff>=0.1.0; extra == "dev"
Requires-Dist: mypy>=1.0.0; extra == "dev"
Dynamic: license-file
